{"": [137, 1172, 0], "Introduction": [1173, 6643, 0], "Empirical patterns of virus decay": [6653, 8020, 0], "Mechanistic model for temperature and humidity effects": [8021, 15779, 0], "Model fitting and prediction of unobserved conditions": [15780, 20464, 0], "Results": [6644, 20464, 1], "Discussion": [20465, 31083, 0], "Viruses and titration": [31131, 31600, 0], "Virus stability experiment": [31601, 32740, 0], "Evaporation experiment": [32741, 33624, 0], "Laboratory experiments": [31107, 33624, 1], "Statistical analyses and mathematical modeling": [33625, 35161, 0], "Meta-analysis": [35162, 37106, 0], "Visualization": [37107, 37277, 0], "Materials and methods": [31084, 37277, 1]}