{"": [107, 142, 0, 143, 1077, 0, 1078, 1105, 0, 1116, 2066, 0, 2067, 3477, 0, 3478, 4489, 0], "SARS-CoV-2 neutralizing antibody isolation strategy.": [4490, 5548, 0], "Development of viral neutralization assays": [5549, 7585, 0], "Establishment of a SARS-CoV-2 cohort": [7586, 9446, 0], "Antibody isolation and preliminary functional screens for down-selection": [9447, 12800, 0], "Functional activity of down-selected antibodies": [12801, 17879, 0], "Passive transfer of neutralizing antibodies and SARS-CoV-2 challenge in Syrian hamsters": [17880, 21946, 0], "Discussion": [21947, 28304, 0]}